jqadaptor/__init__.py
jqadaptor/fetcher.py
zillionare_omega_adaptors_jq-1.1.0.dist-info/AUTHORS.rst
zillionare_omega_adaptors_jq-1.1.0.dist-info/LICENSE
zillionare_omega_adaptors_jq-1.1.0.dist-info/METADATA
zillionare_omega_adaptors_jq-1.1.0.dist-info/WHEEL
zillionare_omega_adaptors_jq-1.1.0.dist-info/top_level.txt
zillionare_omega_adaptors_jq-1.1.0.dist-info/RECORD
