Metadata-Version: 2.1
Name: zillionare-omega-adaptors-jq
Version: 1.1.0
Summary: Jqdatasdk adapter for zillionare omega
Home-page: https://github.com/zillionare/omega_jqadaptor
Author: Aaron Yang
Author-email: code@jieyu.ai
License: MIT license
Keywords: zillionare,omega,adaptors,jqdatasdk
Platform: UNKNOWN
Classifier: Development Status :: 3 - Alpha
Classifier: Intended Audience :: Developers
Classifier: License :: OSI Approved :: MIT License
Classifier: Natural Language :: English
Classifier: Programming Language :: Python :: 3.8
Requires-Python: >=3.8
Requires-Dist: arrow (>=0.15)
Requires-Dist: ruamel.yaml (>=0.16)
Requires-Dist: numpy (>=1.8)
Requires-Dist: jqdatasdk (==1.8.9)
Requires-Dist: SQLAlchemy (<1.4,>=1.3.23)
Requires-Dist: pytz (>=2019.3)
Requires-Dist: cfg4py (>=0.8)
Requires-Dist: zillionare-core-types (>=0.4.0)
